retrievepankey/__init__.py
retrievepankey/retkey.py
retrievepankey/retrievepankey.py
retrievepankey/testretkey.py
retrievepankey-0.1.5.dist-info/LICENSE
retrievepankey-0.1.5.dist-info/METADATA
retrievepankey-0.1.5.dist-info/WHEEL
retrievepankey-0.1.5.dist-info/top_level.txt
retrievepankey-0.1.5.dist-info/RECORD
