Metadata-Version: 2.1
Name: retrievepankey
Version: 0.1.5
Summary: Shortcut functions for coding and working with PAN devices.
Home-page: UNKNOWN
Author: Brian Trost
Author-email: trostb@gmail.com
License: UNKNOWN
Platform: UNKNOWN
Classifier: Programming Language :: Python :: 3
Classifier: License :: OSI Approved :: MIT License
Classifier: Operating System :: OS Independent
